stream4py/__init__.py
stream4py/__main__.py
stream4py/_version.py
stream4py/functional.py
stream4py/http_utils.py
stream4py/lazy_utils.py
stream4py/py.typed
stream4py-0.1.4.dist-info/METADATA
stream4py-0.1.4.dist-info/WHEEL
stream4py-0.1.4.dist-info/entry_points.txt
stream4py-0.1.4.dist-info/licenses/LICENSE.txt
stream4py-0.1.4.dist-info/RECORD
